LICENSE
MANIFEST.in
README.rst
setup.cfg
setup.py
django_saas_billing.egg-info/PKG-INFO
django_saas_billing.egg-info/SOURCES.txt
django_saas_billing.egg-info/dependency_links.txt
django_saas_billing.egg-info/requires.txt
django_saas_billing.egg-info/top_level.txt
saas_billing/__init__.py
saas_billing/app_settings.py
saas_billing/models.py
saas_billing/provider.py
saas_billing/serializers.py
saas_billing/signals.py
saas_billing/urls.py
saas_billing/views.py
saas_billing/webhook_urls.py
saas_billing/management/commands/__init__.py
saas_billing/management/commands/billing.py
saas_billing/management/commands/process_subscriptions.py
saas_billing/migrations/0001_initial.py
saas_billing/migrations/0002_paypalsubscription_paypalsubscriptionplan_paypalsubscriptionplancost_stripecustomer_stripesubscripti.py
saas_billing/migrations/0003_remove_stripesubscription_session_ref.py
saas_billing/migrations/0004_auto_20200915_1507.py
saas_billing/migrations/__init__.py