Metadata-Version: 2.1
Name: django-saas-billing
Version: 0.1.0
Summary: The fastest django billing app that provides subscription and billing for django saas apps with paypal and stripe payment
Home-page: https://github.com/ydaniels/django-saas-billing
Author: Yomi Daniel
Author-email: yomid4all@gmail.com
License: BSD
Platform: UNKNOWN
Classifier: Development Status :: 2 - Pre-Alpha
Classifier: Environment :: Web Environment
Classifier: Framework :: Django
Classifier: Intended Audience :: Developers
Classifier: License :: OSI Approved :: BSD License
Classifier: Operating System :: OS Independent
Classifier: Natural Language :: English
Classifier: Programming Language :: Python :: 2
Classifier: Programming Language :: Python :: 2.7
Classifier: Programming Language :: Python :: 3
Classifier: Programming Language :: Python :: 3.3
Classifier: Programming Language :: Python :: 3.4
Classifier: Topic :: Internet :: WWW/HTTP
License-File: LICENSE
